soothingsounds/__init__.py
soothingsounds/generator.py
soothingsounds/plots.py
soothingsounds/signal_acoustics.py
soothingsounds-1.0.0.dist-info/METADATA
soothingsounds-1.0.0.dist-info/RECORD
soothingsounds-1.0.0.dist-info/WHEEL
soothingsounds-1.0.0.dist-info/top_level.txt
