Metadata-Version: 2.1
Name: soothingsounds
Version: 1.0.0
Summary: Generate a variety of white/brown/pink noises good for relaxation
Home-page: https://github.com/scivision/soothing-sounds
Author: Michael Hirsch, Ph.D
License: UNKNOWN
Platform: UNKNOWN
Classifier: Development Status :: 5 - Production/Stable
Classifier: Environment :: Console
Classifier: Intended Audience :: End Users/Desktop
Classifier: Operating System :: OS Independent
Classifier: Programming Language :: Python :: 3.6
Classifier: Programming Language :: Python :: 3.7
Requires-Python: >=3.6
Provides-Extra: tests
Provides-Extra: io
Requires-Dist: numpy
Requires-Dist: sounddevice
Provides-Extra: io
Requires-Dist: scipy; extra == 'io'
Requires-Dist: pyfftw; extra == 'io'
Provides-Extra: tests
Requires-Dist: pytest; extra == 'tests'
Requires-Dist: coveralls; extra == 'tests'
Requires-Dist: flake8; extra == 'tests'
Requires-Dist: mypy; extra == 'tests'
